clipmcp/__init__.py
clipmcp/__main__.py
clipmcp/cli.py
clipmcp/main.py
clipmcp/server.py
clipmcp/models/__init__.py
clipmcp/models/request.py
clipmcp/models/response.py
clipmcp/routers/__init__.py
clipmcp/routers/api.py
clipmcp/services/__init__.py
clipmcp/services/image_service.py
clipmcp/services/model_service.py
clipmcp/utils/__init__.py
clipmcp/utils/auth.py
clipmcp/utils/config.py
clipmcp-0.2.3.dist-info/licenses/LICENSE
clipmcp-0.2.3.dist-info/METADATA
clipmcp-0.2.3.dist-info/WHEEL
clipmcp-0.2.3.dist-info/entry_points.txt
clipmcp-0.2.3.dist-info/top_level.txt
clipmcp-0.2.3.dist-info/RECORD
