Metadata-Version: 2.4
Name: clipmcp
Version: 0.2.3
Summary: Video processing MCP server
Home-page: https://github.com/example/VideoMCP
Author: VideoMCP Team
Author-email: Your Name <your.email@example.com>
License: MIT
Classifier: Programming Language :: Python :: 3
Classifier: Operating System :: OS Independent
Requires-Python: >=3.8
License-File: LICENSE
Dynamic: license-file
